pywarden/__init__.py
pywarden/main.py
pywarden/api/__init__.py
pywarden/api/get_ids.py
pywarden/api/token.py
pywarden/classes/__init__.py
pywarden/classes/classes.py
pywarden/cli/__init__.py
pywarden/cli/create_collection.py
pywarden/cli/create_item.py
pywarden/cli/gen_secret.py
pywarden/cli/general_tasks.py
pywarden/cli/get_items.py
pywarden/cli/get_list.py
pywarden/cli/get_template.py
pywarden/handler/__init__.py
pywarden/handler/arg_parse.py
pywarden/logger/__init__.py
pywarden/logger/logger.py
pywarden/login/login.py
pywarden/login/status.py
pywarden/login/sync.py
pywarden/login/unlock.py
pywarden/pywarden/__init__.py
pywarden/pywarden/conf_file.py
pywarden/pywarden/gen_config.py
pywarden/pywarden/handle_config.py
pywarden/pywarden/version.py
PyWarden-0.1.7.dist-info/LICENSE
PyWarden-0.1.7.dist-info/METADATA
PyWarden-0.1.7.dist-info/WHEEL
PyWarden-0.1.7.dist-info/entry_points.txt
PyWarden-0.1.7.dist-info/top_level.txt
PyWarden-0.1.7.dist-info/RECORD
